uupt_mcp_freight_server/__init__.py
uupt_mcp_freight_server/__main__.py
uupt_mcp_freight_server/order.py
uupt_mcp_freight_server-0.0.1.dist-info/licenses/LICENSE
uupt_mcp_freight_server-0.0.1.dist-info/METADATA
uupt_mcp_freight_server-0.0.1.dist-info/WHEEL
uupt_mcp_freight_server-0.0.1.dist-info/entry_points.txt
uupt_mcp_freight_server-0.0.1.dist-info/top_level.txt
uupt_mcp_freight_server-0.0.1.dist-info/RECORD
